opencv_video_capture/__init__.py
opencv_video_capture/main.py
opencv_video_capture-0.4.1.dist-info/METADATA
opencv_video_capture-0.4.1.dist-info/WHEEL
opencv_video_capture-0.4.1.dist-info/entry_points.txt
opencv_video_capture-0.4.1.dist-info/top_level.txt
opencv_video_capture-0.4.1.dist-info/RECORD
