Metadata-Version: 2.4
Name: opencv-video-capture
Version: 0.4.1
Summary: Dora Node for capturing video with OpenCV
Author-email: Haixuan Xavier Tao <tao.xavier@outlook.com>, Enzo Le Van <dev@enzo-le-van.fr>
License: MIT
Requires-Python: >=3.8
Requires-Dist: dora-rs>=0.3.9
Requires-Dist: numpy
Requires-Dist: opencv-python>=4.1.1
